polyglotiq/__init__.py
polyglotiq/constants.py
polyglotiq/detector_model.py
polyglotiq/rule_filter.py
PolyglotIQ-0.0.8.dist-info/LICENSE
PolyglotIQ-0.0.8.dist-info/METADATA
PolyglotIQ-0.0.8.dist-info/WHEEL
PolyglotIQ-0.0.8.dist-info/top_level.txt
PolyglotIQ-0.0.8.dist-info/RECORD
